Metadata-Version: 1.0
Name: TelegraMenu
Version: 0.0.1
Summary: Telegram Menus
Home-page: https://github.com/YoilyL/TelegraMenu
Author: Yoily
Author-email: yoilyl@telegram.org
License: GPL
Platform: UNKNOWN
